{"type":"FeatureCollection","features":[{"type":"Feature","properties":{"title":"San Pablo 1825, Santiago de Chile, Región Metropolitana de Santiago 8320000, Chile","description":"vidrio","fill":"#877e17"},"geometry":{"coordinates":[-70.66327023860067,-33.4347034966732],"type":"Point"}},{"type":"Feature","properties":{"title":"Avenida Ricardo Cumming 662, Santiago de Chile, Región Metropolitana de Santiago 8320000, Chile","description":"vidrio","fill":"#877e17"},"geometry":{"coordinates":[-70.66874427015807,-33.43719038596896],"type":"Point"}},{"type":"Feature","properties":{"title":"Almirante Barroso 452, Santiago de Chile, Región Metropolitana de Santiago 8320000, Chile","description":"vidrio","fill":"#877e17"},"geometry":{"coordinates":[-70.66237615625492,-33.43846855862272],"type":"Point"}}]}